LICENSE.txt
MANIFEST.in
README.txt
RELEASE-VERSION
ez_setup.py
libevent.py
setup.cfg
setup.py
version.py
python_libevent.egg-info/PKG-INFO
python_libevent.egg-info/SOURCES.txt
python_libevent.egg-info/dependency_links.txt
python_libevent.egg-info/top_level.txt
src/_libevent.c
src/pybase.c
src/pybase.h
src/pybuffer.c
src/pybuffer.h
src/pybufferevent.c
src/pybufferevent.h
src/pyevent.c
src/pyevent.h
src/pyhttp.c
src/pyhttp.h
src/pylistener.c
src/pylistener.h
tests/__init__.py
tests/test_buffer.py
tests/test_bufferevent.py
tests/test_event.py
tests/test_http.py