Metadata-Version: 1.0
Name: python-libevent
Version: 0.9.2
Summary: Python bindings for libevent
Home-page: http://www.joachim-bauch.de/projects/python-libevent/
Author: Joachim Bauch
Author-email: mail@joachim-bauch.de
License: LGPL
Download-URL: http://pypi.python.org/pypi/python-libevent/
Keywords: libevent network
Platform: UNKNOWN
Classifier: Development Status :: 5 - Production/Stable
Classifier: Programming Language :: Python
Classifier: Topic :: Software Development :: Libraries :: Python Modules
Classifier: Intended Audience :: Developers
Classifier: License :: OSI Approved :: GNU Library or Lesser General Public License (LGPL)
Classifier: Operating System :: OS Independent
